pyuepak/__init__.py
pyuepak/cli.py
pyuepak/entry.py
pyuepak/file_io.py
pyuepak/footer.py
pyuepak/index.py
pyuepak/oodle.py
pyuepak/pak.py
pyuepak/utils.py
pyuepak/version.py
pyuepak-0.2.3.dist-info/METADATA
pyuepak-0.2.3.dist-info/WHEEL
pyuepak-0.2.3.dist-info/entry_points.txt
pyuepak-0.2.3.dist-info/top_level.txt
pyuepak-0.2.3.dist-info/RECORD
