Metadata-Version: 2.4
Name: pyuepak
Version: 0.2.3
Summary: pyuepak is a Python library for working with Unreal Engine .pak files.
Author-email: stas96111 <stas96111@gmail.com>
License: MIT License
Project-URL: Homepage, https://github.com/stas96111/pyuepak
Classifier: Programming Language :: Python :: 3
Classifier: Operating System :: OS Independent
Requires-Python: >=3.8
